python_hbk/__init__.py
python_hbk/Hbk.py
python_hbk-0.1.3.dist-info/METADATA
python_hbk-0.1.3.dist-info/WHEEL
python_hbk-0.1.3.dist-info/RECORD
