Metadata-Version: 2.1
Name: python-hbk
Version: 0.1.3
Summary: Python tool to work with .hbk bookmark files from Hex Workshop
Home-page: https://github.com/Rivko/python-hbk
Author: Sergey Rivov
Author-email: rvngtn@live.com
Requires-Python: >=3.11,<4.0
Classifier: Programming Language :: Python :: 3
Classifier: Programming Language :: Python :: 3.11
Project-URL: Repository, https://github.com/Rivko/python-hbk
